pyqdb/qdb.py
pyqdb/__init__.py
pyqdb-0.4.dist-info/METADATA
pyqdb-0.4.dist-info/top_level.txt
pyqdb-0.4.dist-info/WHEEL
pyqdb-0.4.dist-info/DESCRIPTION.rst
pyqdb-0.4.dist-info/RECORD
pyqdb-0.4.dist-info/pydist.json
